{
    "models_info": [
        {
            "name": "<class 'sklearn.naive_bayes.MultinomialNB'>",
            "classifier": {
                "alpha": 0.7,
                "class_prior": null,
                "fit_prior": true
            }
        },
        {
            "name": "<class 'sklearn.feature_extraction.text.TfidfVectorizer'>",
            "vectorizer": {
                "analyzer": "word",
                "binary": false,
                "decode_error": "strict",
                "dtype": {
                    "py/type": "numpy.float64"
                },
                "encoding": "utf-8",
                "input": "content",
                "lowercase": false,
                "max_df": 0.8,
                "max_features": null,
                "min_df": 0.01,
                "ngram_range": {
                    "py/tuple": [
                        1,
                        2
                    ]
                },
                "norm": "l2",
                "preprocessor": null,
                "smooth_idf": true,
                "stop_words": null,
                "strip_accents": null,
                "sublinear_tf": false,
                "token_pattern": "(?u)\\b\\w\\w+\\b",
                "tokenizer": null,
                "use_idf": true,
                "vocabulary": null
            }
        }
    ],
    "tags": {
        "details": [
            "Uni Model",
            "MultinomialNB"
        ]
    },
    "timestamp": "2022-01-05T14:37:56.903852",
    "name": "MNB_FBeta_Biigram_8597_Jan05",
    "results": {
        "tn": 495.0,
        "fp": 26.0,
        "fn": 9.0,
        "tp": 76.0,
        "model_acc_score": 0.9422442244224423,
        "model_f1_score": 0.8128342245989305,
        "model_prec_score": 0.7450980392156863,
        "model_recall_score": 0.8941176470588236,
        "model_f2_score": 0.8597285067873304
    },
    "preprocess_config": {
        "handle_unicode": true,
        "handle_emoji": true,
        "handle_email": true,
        "handle_username": true,
        "handle_hashtags": true,
        "handle_url": true,
        "handle_markup": true,
        "handle_retweet": true,
        "handle_case": true,
        "handle_lemmatization": true,
        "handle_stopwords": true,
        "handle_punctuation": true,
        "handle_contractions": true,
        "print_stats": true
    }
}